{"id":"serenity-js-org-website;tells-people-what-they-re-reading;chrome-headless-93-0-4577-63;linux-5-8-0-1041-azure","name":"tells people what they're reading","title":"tells people what they're reading","manual":false,"testSteps":[{"number":1,"description":"Alice navigates to 'https://serenity-js.org'","startTime":1631660892031,"children":[],"reportData":[],"screenshots":[{"screenshot":"photo-linux-chrome-headless-93.0.4577.63-alice-navigates-to-https-s-b839f94a75.png","timeStamp":1631660893588}],"duration":1020,"result":"SUCCESS"},{"number":2,"description":"Alice clicks on the accept cookies button","startTime":1631660893594,"children":[],"reportData":[],"screenshots":[{"screenshot":"photo-linux-chrome-headless-93.0.4577.63-alice-clicks-on-the-accept-co-7d237e7594.png","timeStamp":1631660894122}],"duration":39,"result":"SUCCESS"},{"number":3,"description":"Alice ensures that the title of the current page does include 'Serenity/JS'","startTime":1631660894128,"children":[],"reportData":[],"screenshots":[{"screenshot":"photo-linux-chrome-headless-93.0.4577.63-alice-ensures-that-the-title-b64e43ca59.png","timeStamp":1631660894621}],"duration":4,"result":"SUCCESS"}],"userStory":{"id":"serenity-js-org-website","storyName":"serenity-js.org website","path":"","type":"feature"},"startTime":1631660892016,"context":"chrome,linux","driver":"Chrome Headless","tags":[{"name":"Chrome Headless 93.0.4577.63","type":"browser","browserName":"Chrome Headless","browserVersion":"93.0.4577.63","displayName":"Chrome Headless 93.0.4577.63"},{"name":"linux 5.8.0-1041-azure","type":"platform","platformName":"linux","platformVersion":"5.8.0-1041-azure","displayName":"linux 5.8.0-1041-azure"},{"name":"serenity-js.org website","type":"feature","displayName":"serenity-js.org website"}],"featureTag":{"name":"serenity-js.org website","type":"feature","displayName":"serenity-js.org website"},"testSource":"Mocha","result":"SUCCESS","duration":2610}